PythonCPSolver/__init__.py
PythonCPSolver/brancher.py
PythonCPSolver/engine.py
PythonCPSolver/propagators.py
PythonCPSolver/variables.py
PythonCPSolver-0.0.1.dist-info/LICENSE
PythonCPSolver-0.0.1.dist-info/METADATA
PythonCPSolver-0.0.1.dist-info/WHEEL
PythonCPSolver-0.0.1.dist-info/top_level.txt
PythonCPSolver-0.0.1.dist-info/RECORD
